multitasker/__init__.py
multitasker/base.py
multitasker/cli/__init__.py
multitasker/cli/main.py
multitasker/common/__init__.py
multitasker/common/event.py
multitasker/exceptions.py
multitasker/filesystem.py
multitasker/models/__init__.py
multitasker/models/base.py
multitasker/models/constants.py
multitasker/models/enums.py
multitasker/models/task.py
multitasker/multi_worker/__init__.py
multitasker/multi_worker/enums.py
multitasker/multi_worker/models.py
multitasker/multi_worker/multi_worker.py
multitasker/progress.py
multitasker-0.0.7.dist-info/entry_points.txt
multitasker-0.0.7.dist-info/LICENSE
multitasker-0.0.7.dist-info/WHEEL
multitasker-0.0.7.dist-info/METADATA
multitasker-0.0.7.dist-info/RECORD
